swi_ml/__init__.py
swi_ml/backend.py
swi_ml/logs.py
swi_ml/classification/__init__.py
swi_ml/classification/logistic_regression.py
swi_ml/classification/naive_bayes.py
swi_ml/regression/__init__.py
swi_ml/regression/linear_regression.py
swi_ml/svm/__init__.py
swi_ml/svm/svm.py
swi_ml/utils/__init__.py
swi_ml/utils/activations.py
swi_ml/utils/distributions.py
swi_ml/utils/manipulations.py
swi_ml/utils/regularisers.py
tests/__init__.py
tests/test_linear_regression.py
tests/test_logistic_regression.py
tests/test_naive_bayes.py
tests/test_svm.py
swi_ml-0.0.1.dist-info/LICENSE
swi_ml-0.0.1.dist-info/METADATA
swi_ml-0.0.1.dist-info/WHEEL
swi_ml-0.0.1.dist-info/top_level.txt
swi_ml-0.0.1.dist-info/RECORD
