Metadata-Version: 2.1
Name: swi-ml
Version: 0.0.1
Summary: A machine learning library written from scratch - with runtime switchable backend!
Home-page: https://github.com/aitikgupta/swi-ml
Author: Aitik Gupta
Author-email: aitikgupta@gmail.com
License: UNKNOWN
Platform: UNKNOWN
Classifier: Programming Language :: Python :: 3
Classifier: License :: OSI Approved :: MIT License
Classifier: Operating System :: OS Independent
Requires-Python: >=3.6
